llama_index/llms/mymagic/__init__.py
llama_index/llms/mymagic/base.py
llama_index_llms_mymagic-0.4.1.dist-info/METADATA
llama_index_llms_mymagic-0.4.1.dist-info/WHEEL
llama_index_llms_mymagic-0.4.1.dist-info/licenses/LICENSE
llama_index_llms_mymagic-0.4.1.dist-info/RECORD
