Metadata-Version: 2.4
Name: llama-index-llms-mymagic
Version: 0.4.1
Summary: llama-index llms mymagic integration
Author-email: Vitali Avagyan <vitali@mymagic.ai>
License-Expression: MIT
License-File: LICENSE
Requires-Python: <4.0,>=3.9
Requires-Dist: llama-index-core<0.15,>=0.13.0
